VerilogCode/numberConverterRework.v
// Changing numberConverter to use a more clearly defined state machine.
// This will improve clarity to the module, and ideally allow the passthrough of correctly
// formatted BCD values without the current conversion that takes place in calcStateMachine.
// Idealy should also handle negative numbers
// Maintaining this as a very general file, to allow its use in future projects.

module numberConverterRework (
    input  wire clk,
    input  wire startB, 
    input  wire startD, // startB, startD are pulsed high one clock cycle to begin.
    input  wire [24:0] bin, // Input to be converted first
    input  wire [31:0] din, // Input to be passed through directly
    output reg  [3:0]  d1, d2, d3, d4, d5, d6, d7, d8,
    output reg done // Only required for testing.
);


localparam Waiting = 3'd0;
localparam BcdHandling = 3'd1;
localparam BinInitialization = 3'd2;
localparam BinHandling = 3'd3;

reg [2:0] state = Waiting;
reg latchB, latchD;


reg [24:0] binReg;
reg [31:0] dinReg; // Unused
reg [31:0] bcdReg;
reg [31:0] bcdNext;
reg [4:0]  count;
reg busyB = 0;
reg busyD = 0;

always @(posedge clk) begin

    if (startB) begin
        latchB <= 1;
        state <= Waiting;
    end else if (startD) begin
        latchD <= 1;
        state <= Waiting;
    end

    case (state)

    Waiting: begin

        if (startB || latchB) begin
            state <= BinInitialization;
            latchB <= 0;
        end else if (startD || latchD) begin
            state <= BcdHandling;
            latchD <= 0;
        end
        done <= 0;

    end

    BcdHandling: begin

        bcdReg <= din;
        done <= 1;

    end

    BinInitialization: begin

        binReg <= bin;
        bcdReg <= 32'd0;
        count   <= 5'd0;
        state <= BinHandling;

    end

    BinHandling: begin

        if (count < 25) begin
            bcdNext = bcdReg; // blocking assignment (combinational temp)

            // Add 3 step
            if (bcdNext[ 3: 0] >= 5) bcdNext[ 3: 0] = bcdNext[ 3: 0] + 3;
            if (bcdNext[ 7: 4] >= 5) bcdNext[ 7: 4] = bcdNext[ 7: 4] + 3;
            if (bcdNext[11: 8] >= 5) bcdNext[11: 8] = bcdNext[11: 8] + 3;
            if (bcdNext[15:12] >= 5) bcdNext[15:12] = bcdNext[15:12] + 3;
            if (bcdNext[19:16] >= 5) bcdNext[19:16] = bcdNext[19:16] + 3;
            if (bcdNext[23:20] >= 5) bcdNext[23:20] = bcdNext[23:20] + 3;
            if (bcdNext[27:24] >= 5) bcdNext[27:24] = bcdNext[27:24] + 3;
            if (bcdNext[31:28] >= 5) bcdNext[31:28] = bcdNext[31:28] + 3;

            // Shift 
            bcdReg <= {bcdNext[30:0], binReg[24]};
            binReg <= {binReg[23:0], 1'b0};

            count <= count + 1'b1;
        end
        else begin
            state <= Waiting;
            done <= 1'b1;
        end

    end

    endcase

    d8 <= (bcdReg[31:28] == 0) ? 4'hA : bcdReg[31:28];
    d7 <= (bcdReg[31:24] == 0) ? 4'hA : bcdReg[27:24];
    d6 <= (bcdReg[31:20] == 0) ? 4'hA : bcdReg[23:20];
    d5 <= (bcdReg[31:16] == 0) ? 4'hA : bcdReg[19:16];
    d4 <= (bcdReg[31:12] == 0) ? 4'hA : bcdReg[15:12];
    d3 <= (bcdReg[31: 8] == 0) ? 4'hA : bcdReg[11: 8];
    d2 <= (bcdReg[31: 4] == 0) ? 4'hA : bcdReg[ 7: 4];
    d1 <= bcdReg[3:0];

end

endmodule

VerilogCode/numberConverterRework_tb.v
`timescale 1ns / 1ps

module test;

    // Testbench signals
    reg         clk;
    reg         startB;
    reg         startD;
    reg  [24:0] bin;
    reg [31:0] din;
    wire [3:0]  d1, d2, d3, d4, d5, d6, d7, d8;
    wire        done;

    // Instantiate DUT
    numberConverterRework dut (
        .clk   (clk),
        .startB (startB),
        .startD (startD),
        .bin   (bin),
        .din (din),
        .d1    (d1), .d2(d2), .d3(d3), .d4(d4),
        .d5    (d5), .d6(d6), .d7(d7), .d8(d8),
        .done  (done)
    );

    // 50 MHz clock (20 ns period)
    initial begin
        clk = 0;
        forever #10 clk = ~clk;
    end

    // Test stimulus
    initial begin
        $dumpfile("numberConverterRework.vcd");
        $dumpvars(0, test);

        startB = 0;
        bin   = 25'd0;

        #100;

        // Test 1: 0
        bin = 25'd0;
        startB = 1; #20; startB = 0;
        wait(done);
        #40;
        $display("0     → %d %d %d %d %d %d %d %d", d8,d7,d6,d5,d4,d3,d2,d1);

        // Test 2: 1
        bin = 25'd1;
        startB = 1; #20; startB = 0;
        wait(done);
        #40;
        $display("1     → %d %d %d %d %d %d %d %d", d8,d7,d6,d5,d4,d3,d2,d1);

        // Test 3: 42
        bin = 25'd67;
        startB = 1; #20; startB = 0;
        wait(done);
        #40;
        $display("67    → %d %d %d %d %d %d %d %d", d8,d7,d6,d5,d4,d3,d2,d1);

        // Test 4: 999999 (should be 0999999 → but we show 8 digits)
        bin = 25'd999999;
        startB = 1; #20; startB = 0;
        wait(done);
        #40;
        $display("999999→ %d %d %d %d %d %d %d %d", d8,d7,d6,d5,d4,d3,d2,d1);

        // Test 5: max ~33M
        din = 32'b0000_0000_0000_0000_0000_0000_1000_0000;     // 2^25 - 1
        startD = 1; #20; startD = 0;
        wait(done);
        #40;
        $display("80   → %d %d %d %d %d %d %d %d", d8,d7,d6,d5,d4,d3,d2,d1);

                // Test 5: max ~33M
        din = 32'b0000_0000_0000_0000_0000_1000_1000_1000;     // 2^25 - 1
        startD = 1; #20; startD = 0;
        wait(done);
        #40;
        $display("888   → %d %d %d %d %d %d %d %d", d8,d7,d6,d5,d4,d3,d2,d1);

        #200;
        $display("Simulation finished.");
        $finish;
    end

endmodule

VerilogCode/numberConverterRework.vcd
$date
	Fri Apr 03 12:19:44 2026
$end
$version
	Icarus Verilog
$end
$timescale
	1ps
$end
$scope module test $end
$var wire 1 ! done $end
$var wire 4 " d8 [3:0] $end
$var wire 4 # d7 [3:0] $end
$var wire 4 $ d6 [3:0] $end
$var wire 4 % d5 [3:0] $end
$var wire 4 & d4 [3:0] $end
$var wire 4 ' d3 [3:0] $end
$var wire 4 ( d2 [3:0] $end
$var wire 4 ) d1 [3:0] $end
$var reg 25 * bin [24:0] $end
$var reg 1 + clk $end
$var reg 32 , din [31:0] $end
$var reg 1 - startB $end
$var reg 1 . startD $end
$scope module dut $end
$var wire 25 / bin [24:0] $end
$var wire 1 + clk $end
$var wire 32 0 din [31:0] $end
$var wire 1 - startB $end
$var wire 1 . startD $end
$var parameter 3 1 BcdHandling $end
$var parameter 3 2 BinHandling $end
$var parameter 3 3 BinInitialization $end
$var parameter 3 4 Waiting $end
$var reg 32 5 bcdNext [31:0] $end
$var reg 32 6 bcdReg [31:0] $end
$var reg 25 7 binReg [24:0] $end
$var reg 1 8 busyB $end
$var reg 1 9 busyD $end
$var reg 5 : count [4:0] $end
$var reg 4 ; d1 [3:0] $end
$var reg 4 < d2 [3:0] $end
$var reg 4 = d3 [3:0] $end
$var reg 4 > d4 [3:0] $end
$var reg 4 ? d5 [3:0] $end
$var reg 4 @ d6 [3:0] $end
$var reg 4 A d7 [3:0] $end
$var reg 4 B d8 [3:0] $end
$var reg 1 ! done $end
$var reg 1 C latchB $end
$var reg 1 D latchD $end
$var reg 3 E state [2:0] $end
$upscope $end
$upscope $end
$enddefinitions $end
$comment Show the parameter values. $end
$dumpall
b0 4
b10 3
b11 2
b1 1
$end
#0
$dumpvars
b0 E
xD
xC
bx B
bx A
bx @
bx ?
bx >
bx =
bx <
bx ;
bx :
09
08
bx 7
bx 6
bx 5
bx 0
b0 /
x.
0-
bx ,
0+
b0 *
bx )
bx (
bx '
bx &
bx %
bx $
bx #
bx "
x!
$end
#10000
0!
1+
#20000
0+
#30000
1+
#40000
0+
#50000
1+
#60000
0+
#70000
1+
#80000
0+
#90000
1+
#100000
0+
1-
#110000
b10 E
0C
1+
#120000
0+
0-
#130000
b11 E
b0 :
b0 6
b0 7
1+
#140000
0+
#150000
b0 )
b0 ;
b1010 (
b1010 <
b1010 '
b1010 =
b1010 &
b1010 >
b1010 %
b1010 ?
b1010 $
b1010 @
b1010 #
b1010 A
b1010 "
b1010 B
b1 :
b0 5
1+
#160000
0+
#170000
b10 :
1+
#180000
0+
#190000
b11 :
1+
#200000
0+
#210000
b100 :
1+
#220000
0+
#230000
b101 :
1+
#240000
0+
#250000
b110 :
1+
#260000
0+
#270000
b111 :
1+
#280000
0+
#290000
b1000 :
1+
#300000
0+
#310000
b1001 :
1+
#320000
0+
#330000
b1010 :
1+
#340000
0+
#350000
b1011 :
1+
#360000
0+
#370000
b1100 :
1+
#380000
0+
#390000
b1101 :
1+
#400000
0+
#410000
b1110 :
1+
#420000
0+
#430000
b1111 :
1+
#440000
0+
#450000
b10000 :
1+
#460000
0+
#470000
b10001 :
1+
#480000
0+
#490000
b10010 :
1+
#500000
0+
#510000
b10011 :
1+
#520000
0+
#530000
b10100 :
1+
#540000
0+
#550000
b10101 :
1+
#560000
0+
#570000
b10110 :
1+
#580000
0+
#590000
b10111 :
1+
#600000
0+
#610000
b11000 :
1+
#620000
0+
#630000
b11001 :
1+
#640000
0+
#650000
1!
b0 E
1+
#660000
0+
#670000
0!
1+
#680000
0+
#690000
b10 E
0C
1+
1-
b1 *
b1 /
#700000
0+
#710000
b11 E
b0 :
b1 7
1+
0-
#720000
0+
#730000
b1 :
b10 7
1+
#740000
0+
#750000
b10 :
b100 7
1+
#760000
0+
#770000
b11 :
b1000 7
1+
#780000
0+
#790000
b100 :
b10000 7
1+
#800000
0+
#810000
b101 :
b100000 7
1+
#820000
0+
#830000
b110 :
b1000000 7
1+
#840000
0+
#850000
b111 :
b10000000 7
1+
#860000
0+
#870000
b1000 :
b100000000 7
1+
#880000
0+
#890000
b1001 :
b1000000000 7
1+
#900000
0+
#910000
b1010 :
b10000000000 7
1+
#920000
0+
#930000
b1011 :
b100000000000 7
1+
#940000
0+
#950000
b1100 :
b1000000000000 7
1+
#960000
0+
#970000
b1101 :
b10000000000000 7
1+
#980000
0+
#990000
b1110 :
b100000000000000 7
1+
#1000000
0+
#1010000
b1111 :
b1000000000000000 7
1+
#1020000
0+
#1030000
b10000 :
b10000000000000000 7
1+
#1040000
0+
#1050000
b10001 :
b100000000000000000 7
1+
#1060000
0+
#1070000
b10010 :
b1000000000000000000 7
1+
#1080000
0+
#1090000
b10011 :
b10000000000000000000 7
1+
#1100000
0+
#1110000
b10100 :
b100000000000000000000 7
1+
#1120000
0+
#1130000
b10101 :
b1000000000000000000000 7
1+
#1140000
0+
#1150000
b10110 :
b10000000000000000000000 7
1+
#1160000
0+
#1170000
b10111 :
b100000000000000000000000 7
1+
#1180000
0+
#1190000
b11000 :
b1000000000000000000000000 7
1+
#1200000
0+
#1210000
b11001 :
b0 7
b1 6
1+
#1220000
0+
#1230000
b1 )
b1 ;
1!
b0 E
1+
#1240000
0+
#1250000
0!
1+
#1260000
0+
#1270000
b10 E
0C
1+
1-
b1000011 *
b1000011 /
#1280000
0+
#1290000
b11 E
b0 :
b0 6
b1000011 7
1+
0-
#1300000
0+
#1310000
b0 )
b0 ;
b1 :
b10000110 7
1+
#1320000
0+
#1330000
b10 :
b100001100 7
1+
#1340000
0+
#1350000
b11 :
b1000011000 7
1+
#1360000
0+
#1370000
b100 :
b10000110000 7
1+
#1380000
0+
#1390000
b101 :
b100001100000 7
1+
#1400000
0+
#1410000
b110 :
b1000011000000 7
1+
#1420000
0+
#1430000
b111 :
b10000110000000 7
1+
#1440000
0+
#1450000
b1000 :
b100001100000000 7
1+
#1460000
0+
#1470000
b1001 :
b1000011000000000 7
1+
#1480000
0+
#1490000
b1010 :
b10000110000000000 7
1+
#1500000
0+
#1510000
b1011 :
b100001100000000000 7
1+
#1520000
0+
#1530000
b1100 :
b1000011000000000000 7
1+
#1540000
0+
#1550000
b1101 :
b10000110000000000000 7
1+
#1560000
0+
#1570000
b1110 :
b100001100000000000000 7
1+
#1580000
0+
#1590000
b1111 :
b1000011000000000000000 7
1+
#1600000
0+
#1610000
b10000 :
b10000110000000000000000 7
1+
#1620000
0+
#1630000
b10001 :
b100001100000000000000000 7
1+
#1640000
0+
#1650000
b10010 :
b1000011000000000000000000 7
1+
#1660000
0+
#1670000
b10011 :
b110000000000000000000 7
b1 6
1+
#1680000
0+
#1690000
b1 )
b1 ;
b10100 :
b1100000000000000000000 7
b10 6
b1 5
1+
#1700000
0+
#1710000
b10 )
b10 ;
b10101 :
b11000000000000000000000 7
b100 6
b10 5
1+
#1720000
0+
#1730000
b100 )
b100 ;
b10110 :
b110000000000000000000000 7
b1000 6
b100 5
1+
#1740000
0+
#1750000
b1000 )
b1000 ;
b10111 :
b1100000000000000000000000 7
b10110 6
b1011 5
1+
#1760000
0+
#1770000
b110 )
b110 ;
b1 (
b1 <
b11000 :
b1000000000000000000000000 7
b110011 6
b11001 5
1+
#1780000
0+
#1790000
b11 )
b11 ;
b11 (
b11 <
b11001 :
b0 7
b1100111 6
b110011 5
1+
#1800000
0+
#1810000
b111 )
b111 ;
b110 (
b110 <
1!
b0 E
1+
#1820000
0+
#1830000
0!
1+
#1840000
0+
#1850000
b10 E
0C
1+
1-
b11110100001000111111 *
b11110100001000111111 /
#1860000
0+
#1870000
b11 E
b0 :
b0 6
b11110100001000111111 7
1+
0-
#1880000
0+
#1890000
b0 )
b0 ;
b1010 (
b1010 <
b1 :
b111101000010001111110 7
b0 5
1+
#1900000
0+
#1910000
b10 :
b1111010000100011111100 7
1+
#1920000
0+
#1930000
b11 :
b11110100001000111111000 7
1+
#1940000
0+
#1950000
b100 :
b111101000010001111110000 7
1+
#1960000
0+
#1970000
b101 :
b1111010000100011111100000 7
1+
#1980000
0+
#1990000
b110 :
b1110100001000111111000000 7
b1 6
1+
#2000000
0+
#2010000
b1 )
b1 ;
b111 :
b1101000010001111110000000 7
b11 6
b1 5
1+
#2020000
0+
#2030000
b11 )
b11 ;
b1000 :
b1010000100011111100000000 7
b111 6
b11 5
1+
#2040000
0+
#2050000
b111 )
b111 ;
b1001 :
b100001000111111000000000 7
b10101 6
b1010 5
1+
#2060000
0+
#2070000
b101 )
b101 ;
b1 (
b1 <
b1010 :
b1000010001111110000000000 7
b110000 6
b11000 5
1+
#2080000
0+
#2090000
b0 )
b0 ;
b11 (
b11 <
b1011 :
b100011111100000000000 7
b1100001 6
b110000 5
1+
#2100000
0+
#2110000
b1 )
b1 ;
b110 (
b110 <
b1100 :
b1000111111000000000000 7
b100100010 6
b10010001 5
1+
#2120000
0+
#2130000
b10 )
b10 ;
b10 (
b10 <
b1 '
b1 =
b1101 :
b10001111110000000000000 7
b1001000100 6
b100100010 5
1+
#2140000
0+
#2150000
b100 )
b100 ;
b100 (
b100 <
b10 '
b10 =
b1110 :
b100011111100000000000000 7
b10010001000 6
b1001000100 5
1+
#2160000
0+
#2170000
b1000 )
b1000 ;
b1000 (
b1000 <
b100 '
b100 =
b1111 :
b1000111111000000000000000 7
b100101110110 6
b10010111011 5
1+
#2180000
0+
#2190000
b110 )
b110 ;
b111 (
b111 <
b1001 '
b1001 =
b10000 :
b1111110000000000000000 7
b1100101010011 6
b110010101001 5
1+
#2200000
0+
#2210000
b11 )
b11 ;
b101 (
b101 <
b1 &
b1 >
b10001 :
b11111100000000000000000 7
b11100100000110 6
b1110010000011 5
1+
#2220000
0+
#2230000
b110 )
b110 ;
b0 (
b0 <
b11 &
b11 >
b10010 :
b111111000000000000000000 7
b111100000010010 6
b11110000001001 5
1+
#2240000
0+
#2250000
b10 )
b10 ;
b1 (
b1 <
b1000 '
b1000 =
b111 &
b111 >
b10011 :
b1111110000000000000000000 7
b10101011000100100 6
b1010101100010010 5
1+
#2260000
0+
#2270000
b100 )
b100 ;
b10 (
b10 <
b110 '
b110 =
b101 &
b101 >
b1 %
b1 ?
b10100 :
b1111100000000000000000000 7
b110001001001001001 6
b11000100100100100 5
1+
#2280000
0+
#2290000
b1001 )
b1001 ;
b100 (
b100 <
b10 '
b10 =
b1 &
b1 >
b11 %
b11 ?
b10101 :
b1111000000000000000000000 7
b1100010010010011001 6
b110001001001001100 5
1+
#2300000
0+
#2310000
b1001 (
b1001 <
b100 '
b100 =
b10 &
b10 >
b110 %
b110 ?
b10110 :
b1110000000000000000000000 7
b100100100100110011001 6
b10010010010011001100 5
1+
#2320000
0+
#2330000
b1001 '
b1001 =
b100 &
b100 >
b10 %
b10 ?
b1 $
b1 @
b10111 :
b1100000000000000000000000 7
b1001001001100110011001 6
b100100100110011001100 5
1+
#2340000
0+
#2350000
b1001 &
b1001 >
b100 %
b100 ?
b10 $
b10 @
b11000 :
b1000000000000000000000000 7
b10010011001100110011001 6
b1001001100110011001100 5
1+
#2360000
0+
#2370000
b1001 %
b1001 ?
b100 $
b100 @
b11001 :
b0 7
b100110011001100110011001 6
b10011001100110011001100 5
1+
#2380000
0+
#2390000
b1001 $
b1001 @
1!
b0 E
1+
#2400000
0+
#2410000
0!
1+
#2420000
0+
#2430000
b1 E
0D
1+
1.
b10000000 ,
b10000000 0
#2440000
0+
#2450000
1!
b10000000 6
1+
0.
#2460000
0+
#2470000
b0 )
b0 ;
b1000 (
b1000 <
b1010 '
b1010 =
b1010 &
b1010 >
b1010 %
b1010 ?
b1010 $
b1010 @
1+
#2480000
0+
#2490000
b100010001000 6
b0 E
1D
1+
1.
b100010001000 ,
b100010001000 0
#2500000
0+
#2510000
b1000 )
b1000 ;
b1000 '
b1000 =
0!
0D
b1 E
1+
0.
#2520000
0+
#2530000
1!
1+
